MANIFEST.in
README.rst
requirements.txt
setup.cfg
setup.py
sequana_merge_flowcells.egg-info/PKG-INFO
sequana_merge_flowcells.egg-info/SOURCES.txt
sequana_merge_flowcells.egg-info/dependency_links.txt
sequana_merge_flowcells.egg-info/entry_points.txt
sequana_merge_flowcells.egg-info/not-zip-safe
sequana_merge_flowcells.egg-info/requires.txt
sequana_merge_flowcells.egg-info/top_level.txt
sequana_pipelines/merge_flowcells/__init__.py
sequana_pipelines/merge_flowcells/config.yaml
sequana_pipelines/merge_flowcells/main.py
sequana_pipelines/merge_flowcells/merge_flowcells.rules
sequana_pipelines/merge_flowcells/requirements.txt
sequana_pipelines/merge_flowcells/schema.yaml
sequana_pipelines/merge_flowcells/data/__init__.py
test/test_main.py